verse-1.7.dist-info/METADATA
verse-1.7.dist-info/RECORD
verse-1.7.dist-info/WHEEL
verse-1.7.dist-info/entry_points.txt
verse-1.7.dist-info/top_level.txt
versesrc/__init__.py
versesrc/verse.py
