Metadata-Version: 2.1
Name: verse
Version: 1.7
Summary: Verse allow you to define easy instruction and commands for each of your project !
Home-page: https://github.com/ethanquix/verse
Author: dwyzlic
Author-email: dimitriwyzlic@gmail.com
License: MIT
Platform: UNKNOWN
Classifier: Programming Language :: Python :: 3
Classifier: License :: OSI Approved :: MIT License
Classifier: Operating System :: OS Independent
